setup.py
frasco_admin/__init__.py
frasco_admin/macros.html
frasco_admin/view.py
frasco_admin.egg-info/PKG-INFO
frasco_admin.egg-info/SOURCES.txt
frasco_admin.egg-info/dependency_links.txt
frasco_admin.egg-info/not-zip-safe
frasco_admin.egg-info/requires.txt
frasco_admin.egg-info/top_level.txt
frasco_admin/blueprint/__init__.py
frasco_admin/blueprint/static/admin.js
frasco_admin/blueprint/static/layout.css
frasco_admin/blueprint/templates/admin/dashboard.html
frasco_admin/blueprint/templates/admin/layout.html