Metadata-Version: 1.0
Name: frasco-admin
Version: 0.2.1
Summary: Admin interface for Frasco
Home-page: http://github.com/frascoweb/frasco-admin
Author: Maxime Bouroumeau-Fuseau
Author-email: maxime.bouroumeau@gmail.com
License: MIT
Platform: any
